odoo/addons/account_ecotax_tax/README.rst
odoo/addons/account_ecotax_tax/__init__.py
odoo/addons/account_ecotax_tax/__manifest__.py
odoo/addons/account_ecotax_tax/i18n/account_ecotax_tax.pot
odoo/addons/account_ecotax_tax/i18n/it.po
odoo/addons/account_ecotax_tax/models/__init__.py
odoo/addons/account_ecotax_tax/models/account_ecotax_classification.py
odoo/addons/account_ecotax_tax/models/account_move_line.py
odoo/addons/account_ecotax_tax/models/account_tax.py
odoo/addons/account_ecotax_tax/readme/CONTRIBUTORS.rst
odoo/addons/account_ecotax_tax/readme/DESCRIPTION.rst
odoo/addons/account_ecotax_tax/readme/ROADMAP.rst
odoo/addons/account_ecotax_tax/readme/USAGE.rst
odoo/addons/account_ecotax_tax/report/invoice.xml
odoo/addons/account_ecotax_tax/static/description/icon.png
odoo/addons/account_ecotax_tax/static/description/index.html
odoo/addons/account_ecotax_tax/tests/__init__.py
odoo/addons/account_ecotax_tax/tests/test_ecotax.py
odoo/addons/account_ecotax_tax/views/account_ecotax_classification_view.xml
odoo/addons/account_ecotax_tax/views/account_move_view.xml
odoo/addons/account_ecotax_tax/views/account_tax_view.xml
odoo_addon_account_ecotax_tax-16.0.1.0.1.dist-info/METADATA
odoo_addon_account_ecotax_tax-16.0.1.0.1.dist-info/WHEEL
odoo_addon_account_ecotax_tax-16.0.1.0.1.dist-info/top_level.txt
odoo_addon_account_ecotax_tax-16.0.1.0.1.dist-info/RECORD
